aurel/__init__.py
aurel/core.py
aurel/coreanalytic.py
aurel/finitedifference.py
aurel/maths.py
aurel/numerical.py
aurel/reading.py
aurel/solutions/Collins_Stewart.py
aurel/solutions/Conformally_flat.py
aurel/solutions/EdS.py
aurel/solutions/Harvey_Tsoubelis.py
aurel/solutions/ICPertFLRW.py
aurel/solutions/LCDM.py
aurel/solutions/Non_diagonal.py
aurel/solutions/Rosquist_Jantzen.py
aurel/solutions/Schwarzschild_isotropic.py
aurel/solutions/Szekeres.py
aurel/solutions/__init__.py
aurel-2025.5.dist-info/licenses/LICENSE
aurel-2025.5.dist-info/METADATA
aurel-2025.5.dist-info/WHEEL
aurel-2025.5.dist-info/top_level.txt
aurel-2025.5.dist-info/RECORD
