Metadata-Version: 2.4
Name: aurel
Version: 2025.5
Summary: A Python package for general relativity calculations.
Author-email: Robyn L Munoz <r.l.munoz@sussex.ac.uk>
License-Expression: GPL-3.0-or-later
Project-URL: Source, https://github.com/robynlm/aurel
Project-URL: Documentation, https://robynlm.github.io/aurel/
Keywords: numerical relativity,general relativity,simulation,Python,tensor
Classifier: Programming Language :: Python :: 3
Classifier: Operating System :: OS Independent
Requires-Python: >=3.8
License-File: LICENSE
Requires-Dist: numpy
Requires-Dist: matplotlib
Requires-Dist: sympy
Requires-Dist: h5py
Requires-Dist: glob2
Requires-Dist: scipy
Requires-Dist: ipython
Dynamic: license-file
